{
	"$schema": "https://schemas.wp.org/trunk/block.json",
	"apiVersion": 3,
	"name": "axismundi/media-collection",
	"version": "0.1.0",
	"title": "Media Collection",
	"category": "theme",
	"icon": "images-alt2",
	"description": "Displays navigable media folders and attachments as one collection.",
	"textdomain": "axismundi-media-library",
	"attributes": {
		"source": { "type": "string", "default": "current" },
		"ownerId": { "type": "number", "default": 0 },
		"folderId": { "type": "number", "default": 0 },
		"columns": { "type": "number", "default": 3 },
		"perPage": { "type": "number", "default": 12 },
		"imageSize": { "type": "string", "default": "medium_large" },
		"showDates": { "type": "boolean", "default": true },
		"showCounts": { "type": "boolean", "default": true },
		"showUp": { "type": "boolean", "default": true }
	},
	"supports": {
		"html": false,
		"align": [ "wide", "full" ],
		"spacing": { "margin": true, "padding": true }
	},
	"editorScript": "file:./edit.js",
	"editorStyle": "file:./style.css",
	"style": "file:./style.css",
	"render": "file:./render.php"
}
